EXTERNALS.txt
setup.py
ez_setup/README.txt
ez_setup/__init__.py
src/release.py
src/releasemanager/LICENSE.txt
src/releasemanager/QUICKSTART.txt
src/releasemanager/README.txt
src/releasemanager/__init__.py
src/releasemanager/logger.py
src/releasemanager/project.py
src/releasemanager.egg-info/PKG-INFO
src/releasemanager.egg-info/SOURCES.txt
src/releasemanager.egg-info/dependency_links.txt
src/releasemanager.egg-info/entry_points.txt
src/releasemanager.egg-info/namespace_packages.txt
src/releasemanager.egg-info/not-zip-safe
src/releasemanager.egg-info/requires.txt
src/releasemanager.egg-info/top_level.txt
src/releasemanager/auth/__init__.py
src/releasemanager/builder/__init__.py
src/releasemanager/builder/base.py
src/releasemanager/builder/buildhost.py
src/releasemanager/config/__init__.py
src/releasemanager/ctl/__init__.py
src/releasemanager/ctl/ctl_template.py
src/releasemanager/ctl/generate.py
src/releasemanager/ctl/templates/BUILDER.txt
src/releasemanager/ctl/templates/INSTALLER.txt
src/releasemanager/ctl/templates/MANAGER.txt
src/releasemanager/ctl/templates/__init__.py
src/releasemanager/ctl/templates/builder_serve.py
src/releasemanager/ctl/templates/installer_serve.py
src/releasemanager/ctl/templates/manager_serve.py
src/releasemanager/ctl/templates/builder/__init__.py
src/releasemanager/ctl/templates/builder/template.py
src/releasemanager/ctl/templates/builder/utils/__init__.py
src/releasemanager/ctl/templates/builder/utils/template_builder.py
src/releasemanager/ctl/templates/conf/__init__.py
src/releasemanager/ctl/templates/conf/builder/__init__.py
src/releasemanager/ctl/templates/conf/builder/build_host_template.py
src/releasemanager/ctl/templates/conf/builder/build_host_template.xml
src/releasemanager/ctl/templates/conf/builder/release_builder_template.py
src/releasemanager/ctl/templates/conf/builder/release_builder_template.xml
src/releasemanager/ctl/templates/conf/installer/__init__.py
src/releasemanager/ctl/templates/conf/installer/release_installer_template.py
src/releasemanager/ctl/templates/conf/installer/release_installer_template.xml
src/releasemanager/ctl/templates/conf/manager/__init__.py
src/releasemanager/ctl/templates/conf/manager/release_manager_template.py
src/releasemanager/ctl/templates/conf/manager/release_manager_template.xml
