Metadata-Version: 1.0
Name: releasemanager
Version: 1.10
Summary: Allows simple, extensible, distributed release management for complex environments.
Home-page: http://code.google.com/p/releasemanager/
Author: James Taylor
Author-email: baldtrol@gmail.com
License: MIT
Download-URL: http://releasemanager.googlecode.com/svn/trunk/
Keywords: release,software deployment,distributed environment
Platform: UNKNOWN
Classifier: Development Status :: 3 - Alpha
Classifier: Intended Audience :: Developers
Classifier: Intended Audience :: Information Technology
Classifier: Intended Audience :: System Administrators
Classifier: License :: OSI Approved :: MIT License
Classifier: Programming Language :: Python
